tlsprint/__init__.py
tlsprint/cli.py
tlsprint/identify.py
tlsprint/learn.py
tlsprint/connector/TLSAttackerConnector2.0.jar
tlsprint/connector/lib/ModifiableVariable-2.1.jar
tlsprint/connector/lib/TLS-Core-2.1.jar
tlsprint/connector/lib/Transport-2.1.jar
tlsprint/connector/lib/Utils-2.1.jar
tlsprint/connector/lib/bcpkix-jdk15on-1.58.jar
tlsprint/connector/lib/bcprov-debug-jdk15on-1.58.jar
tlsprint/connector/lib/bcprov-jdk15on-1.58.jar
tlsprint/connector/lib/commons-lang3-3.6.jar
tlsprint/connector/lib/jcommander-1.69.jar
tlsprint/connector/lib/log4j-api-2.9.0.jar
tlsprint/connector/lib/log4j-core-2.9.0.jar
tlsprint/data/model.p
tlsprint-0.1.0.dist-info/METADATA
tlsprint-0.1.0.dist-info/WHEEL
tlsprint-0.1.0.dist-info/entry_points.txt
tlsprint-0.1.0.dist-info/top_level.txt
tlsprint-0.1.0.dist-info/RECORD
