Metadata-Version: 2.1
Name: tlsprint
Version: 0.1.0
Summary: Fingerprint TLS implementations
Home-page: https://github.com/ErwinJanssen/tlsprint
Author: Erwin Janssen
Author-email: erwinjanssen@outlook.com
License: UNKNOWN
Platform: UNKNOWN
Requires-Dist: click
Requires-Dist: networkx
Requires-Dist: pydot
